pandamatic/__init__.py
pandamatic-0.1.0.dist-info/LICENSE
pandamatic-0.1.0.dist-info/METADATA
pandamatic-0.1.0.dist-info/WHEEL
pandamatic-0.1.0.dist-info/top_level.txt
pandamatic-0.1.0.dist-info/RECORD
