Metadata-Version: 2.1
Name: pandamatic
Version: 0.1.0
Summary: AI-powered code generator for dataframe processing.
Author: Rio Nur Arifin
Author-email: arifinrio95@gmail.com
Classifier: Programming Language :: Python :: 3
Classifier: License :: OSI Approved :: MIT License
Classifier: Operating System :: OS Independent
Requires-Python: >=3.7
License-File: LICENSE
Requires-Dist: pandas>=1.0.0
Requires-Dist: openai>=1.0.0
Requires-Dist: ipython>=7.0.0
